{"paddingVertical":"48px","paddingHorizontal":"50px","backgroundImage":null,"backgroundImageSelection":null,"backgroundMode":"color","backgroundColor":"rgba(110,115,141,1)","dropShadow":true,"dropShadowOffsetY":"20px","dropShadowBlurRadius":"68px","theme":"theme:1w85oubczid","windowTheme":"none","language":"application/x-sh","fontFamily":"JetBrains Mono","fontSize":"14px","lineHeight":"127%","windowControls":true,"widthAdjustment":true,"lineNumbers":false,"firstLineNumber":1,"exportSize":"2x","watermark":false,"squaredImage":false,"hiddenCharacters":false,"name":"","width":680,"highlights":null}